dlm_engine_updater/__init__.py
dlm_engine_updater/config.py
dlm_engine_updater/lock.py
dlm_engine_updater/logger.py
dlm_engine_updater/plugin.py
dlm_engine_updater/updater.py
dlmengineupdater-1.0.1.dist-info/METADATA
dlmengineupdater-1.0.1.dist-info/WHEEL
dlmengineupdater-1.0.1.dist-info/entry_points.txt
dlmengineupdater-1.0.1.dist-info/licenses/LICENSE.txt
dlmengineupdater-1.0.1.dist-info/RECORD
