Metadata-Version: 2.4
Name: DlmEngineUpdater
Version: 1.0.1
Summary: Distributed Lock Engine API OS Updater
Author-email: "Stephan.Schultchen" <stephan.schultchen@gmail.com>
License: The MIT License (MIT)
License-File: LICENSE.txt
Classifier: Programming Language :: Python
Requires-Python: >=3.4
Requires-Dist: httpx
Requires-Dist: pep3143daemon
Requires-Dist: pydantic
Requires-Dist: pydantic-settings
